{
  "settings": {
    "dt": 0.01,
    "t_end": 2000,
    "driver": "fourier"
  },
  "molecule": {
    "geometry": [
        {"atom": "O", "coord": [ 0.0000000000, 0.0000000000, -0.1302052882]},
        {"atom": "H", "coord": [ 1.4891244004, 0.0000000000,  1.0332262019]},
        {"atom": "H", "coord": [-1.4891244004, 0.0000000000,  1.0332262019]}
    ],
    "geometry_units": "bohr",
    "basis": "631g*",
    "xc": "HYB_GGA_XC_LC_PBEOP",
    "lrc_parameter": 0.581692,
    "propagator": { 
      "type": "magnus2"
    },
    "broadening": {
      "gam0": 1,
      "xi": 0.5,
      "eps0": 0.177536,
      "clamp": 100
    },
    "source": {
      "type": "kick",
      "intensity": 5e-5,
      "peak_time": 0.05,
      "width_steps": 3
    }
  },
  "files": {
    "checkpoint": {
      "filepath": "checkpoint.npz",
      "frequency_time": 1000
    },
    "field_e_filepath": "field_e.csv",
    "field_p_filepath": "field_p.csv",
    "spectra_e_vs_p_filepath": "output.png"
  },
  "additional_parameters": {
    "fourier": {
      "min_ev": 1,
      "max_ev": 35,
      "npz_filepath": "fourier.npz",
      "spectrum_filepath": "spectrum.png"
    }
  }
}